odoo/addons/purchase_line_procurement_group/README.rst
odoo/addons/purchase_line_procurement_group/__init__.py
odoo/addons/purchase_line_procurement_group/__manifest__.py
odoo/addons/purchase_line_procurement_group/i18n/purchase_line_procurement_group.pot
odoo/addons/purchase_line_procurement_group/models/__init__.py
odoo/addons/purchase_line_procurement_group/models/procurement.py
odoo/addons/purchase_line_procurement_group/models/purchase.py
odoo/addons/purchase_line_procurement_group/models/stock_move.py
odoo/addons/purchase_line_procurement_group/static/description/icon.png
odoo/addons/purchase_line_procurement_group/tests/__init__.py
odoo/addons/purchase_line_procurement_group/tests/test_po_line_proc_group.py
odoo/addons/purchase_line_procurement_group/views/purchase.xml
odoo11_addon_purchase_line_procurement_group-11.0.1.1.1.dist-info/METADATA
odoo11_addon_purchase_line_procurement_group-11.0.1.1.1.dist-info/WHEEL
odoo11_addon_purchase_line_procurement_group-11.0.1.1.1.dist-info/top_level.txt
odoo11_addon_purchase_line_procurement_group-11.0.1.1.1.dist-info/RECORD
